{"channel":145,"channelName":"Mark_Rober","content":[{"title":"SKIN A WATERMELON party trick","videoId":"Q6vVuj3iggE","duration":172,"channelId":"UCY1kMZp36IQSyNx_9h4mpCg","uploadDate":"2015-08-31","channelName":"Mark Rober","link":"https://www.youtube.com/watch?v=Q6vVuj3iggE","views":129199024},{"title":"World's Largest Jello Pool- Can you swim in Jello?","videoId":"DPZzrlFCD_I","duration":628,"channelId":"UCY1kMZp36IQSyNx_9h4mpCg","uploadDate":"2019-05-16","channelName":"Mark Rober","link":"https://www.youtube.com/watch?v=DPZzrlFCD_I","views":125843448},{"title":"Backyard Squirrel Maze 1.0- Ninja Warrior Course","videoId":"hFZFjoX2cGg","duration":1221,"channelId":"UCY1kMZp36IQSyNx_9h4mpCg","uploadDate":"2020-05-24","channelName":"Mark Rober","link":"https://www.youtube.com/watch?v=hFZFjoX2cGg","views":109993976},{"title":"Liquid Sand Hot Tub- Fluidized air bed","videoId":"My4RA5I0FKs","duration":549,"channelId":"UCY1kMZp36IQSyNx_9h4mpCg","uploadDate":"2017-11-28","channelName":"Mark Rober","link":"https://www.youtube.com/watch?v=My4RA5I0FKs","views":108483675},{"title":"Testing if Sharks Can Smell a Drop of Blood","videoId":"ugRc5jx80yg","duration":803,"channelId":"UCY1kMZp36IQSyNx_9h4mpCg","uploadDate":"2019-07-28","channelName":"Mark Rober","link":"https://www.youtube.com/watch?v=ugRc5jx80yg","views":102755527},{"title":"CARNIVAL SCAM SCIENCE- and how to win","videoId":"tk_ZlWJ3qJI","duration":653,"channelId":"UCY1kMZp36IQSyNx_9h4mpCg","uploadDate":"2017-10-24","channelName":"Mark Rober","link":"https://www.youtube.com/watch?v=tk_ZlWJ3qJI","views":98199027},{"title":"Glitter Bomb 1.0 vs Porch Pirates","videoId":"xoxhDk-hwuo","duration":491,"channelId":"UCY1kMZp36IQSyNx_9h4mpCg","uploadDate":"2018-12-17","channelName":"Mark Rober","link":"https://www.youtube.com/watch?v=xoxhDk-hwuo","views":88636910},{"title":"World's Largest Elephant Toothpaste Experiment","videoId":"Kou7ur5xt_4","duration":633,"channelId":"UCY1kMZp36IQSyNx_9h4mpCg","uploadDate":"2019-08-29","channelName":"Mark Rober","link":"https://www.youtube.com/watch?v=Kou7ur5xt_4","views":88111002},{"title":"How to Survive a Grenade Blast","videoId":"W4DnuQOtA8E","duration":300,"channelId":"UCY1kMZp36IQSyNx_9h4mpCg","uploadDate":"2016-04-06","channelName":"Mark Rober","link":"https://www.youtube.com/watch?v=W4DnuQOtA8E","views":87350047},{"title":"World's Largest Devil's Toothpaste Explosion","videoId":"BHiWygziyso","duration":1327,"channelId":"UCY1kMZp36IQSyNx_9h4mpCg","uploadDate":"2020-09-20","channelName":"Mark Rober","link":"https://www.youtube.com/watch?v=BHiWygziyso","views":82547642},{"title":"1500 Water Balloons + Trampoline- SLO MO!!","videoId":"edRloa1ZHqY","duration":239,"channelId":"UCY1kMZp36IQSyNx_9h4mpCg","uploadDate":"2016-05-18","channelName":"Mark Rober","link":"https://www.youtube.com/watch?v=edRloa1ZHqY","views":76343995},{"title":"Backyard Squirrel Maze 2.0- The Walnut Heist","videoId":"DTvS9lvRxZ8","duration":1153,"channelId":"UCY1kMZp36IQSyNx_9h4mpCg","uploadDate":"2021-05-18","channelName":"Mark Rober","link":"https://www.youtube.com/watch?v=DTvS9lvRxZ8","views":74507577},{"title":"Shark Attack Test- Human Blood vs. Fish Blood","videoId":"vePc5V4h_kg","duration":997,"channelId":"UCY1kMZp36IQSyNx_9h4mpCg","uploadDate":"2020-08-09","channelName":"Mark Rober","link":"https://www.youtube.com/watch?v=vePc5V4h_kg","views":72002438},{"title":"Glitterbomb Trap Catches Phone Scammer (who gets arrested)","videoId":"VrKW58MS12g","duration":1394,"channelId":"UCY1kMZp36IQSyNx_9h4mpCg","uploadDate":"2021-03-18","channelName":"Mark Rober","link":"https://www.youtube.com/watch?v=VrKW58MS12g","views":70578188},{"title":"Glitter Bomb 2.0 vs Porch Pirates","videoId":"a_TSR_v07m0","duration":1095,"channelId":"UCY1kMZp36IQSyNx_9h4mpCg","uploadDate":"2019-12-15","channelName":"Mark Rober","link":"https://www.youtube.com/watch?v=a_TSR_v07m0","views":68879173},{"title":"World's Longest Field Goal- Robot vs NFL Kicker","videoId":"P_6my53IlxY","duration":1181,"channelId":"UCY1kMZp36IQSyNx_9h4mpCg","uploadDate":"2021-02-06","channelName":"Mark Rober","link":"https://www.youtube.com/watch?v=P_6my53IlxY","views":66222024},{"title":"Pranks Destroy Scam Callers- GlitterBomb Payback","videoId":"xsLJZyih3Ac","duration":1601,"channelId":"UCY1kMZp36IQSyNx_9h4mpCg","uploadDate":"2022-05-08","channelName":"Mark Rober","link":"https://www.youtube.com/watch?v=xsLJZyih3Ac","views":62387809},{"title":"Drinking Nasty Swamp Water (to save the world)","videoId":"6qZWMNW7GmE","duration":668,"channelId":"UCY1kMZp36IQSyNx_9h4mpCg","uploadDate":"2019-02-15","channelName":"Mark Rober","link":"https://www.youtube.com/watch?v=6qZWMNW7GmE","views":61900722},{"title":"FLYING PHONE SCAM EXPOSED (so I built a REAL one)","videoId":"LEZCxxKp0hM","duration":657,"channelId":"UCY1kMZp36IQSyNx_9h4mpCg","uploadDate":"2018-09-27","channelName":"Mark Rober","link":"https://www.youtube.com/watch?v=LEZCxxKp0hM","views":56203199},{"title":"Feeding Bill Gates a Fake Burger (to save the world)","videoId":"-k-V3ESHcfA","duration":999,"channelId":"UCY1kMZp36IQSyNx_9h4mpCg","uploadDate":"2020-02-12","channelName":"Mark Rober","link":"https://www.youtube.com/watch?v=-k-V3ESHcfA","views":55943450},{"title":"World's First Automatic Strike Bowling Ball","videoId":"wM5NHC97JBw","duration":351,"channelId":"UCY1kMZp36IQSyNx_9h4mpCg","uploadDate":"2019-11-14","channelName":"Mark Rober","link":"https://www.youtube.com/watch?v=wM5NHC97JBw","views":55747405},{"title":"25 MILLION Orbeez in a pool- Do you sink or float?","videoId":"MFVXsnq230c","duration":350,"channelId":"UCY1kMZp36IQSyNx_9h4mpCg","uploadDate":"2016-08-16","channelName":"Mark Rober","link":"https://www.youtube.com/watch?v=MFVXsnq230c","views":53483796},{"title":"Glitterbomb 3.0 vs. Porch Pirates","videoId":"h4T_LlK1VE4","duration":1331,"channelId":"UCY1kMZp36IQSyNx_9h4mpCg","uploadDate":"2020-12-16","channelName":"Mark Rober","link":"https://www.youtube.com/watch?v=h4T_LlK1VE4","views":50689189},{"title":"World's LARGEST SUPER SOAKER!! (not clickbait)","videoId":"T1KRQ3RcvXA","duration":485,"channelId":"UCY1kMZp36IQSyNx_9h4mpCg","uploadDate":"2017-07-11","channelName":"Mark Rober","link":"https://www.youtube.com/watch?v=T1KRQ3RcvXA","views":48211965},{"title":"Beating 5 Scam Arcade Games with Science","videoId":"Rsxao9ptdmI","duration":1231,"channelId":"UCY1kMZp36IQSyNx_9h4mpCg","uploadDate":"2022-09-17","channelName":"Mark Rober","link":"https://www.youtube.com/watch?v=Rsxao9ptdmI","views":44663468},{"title":"World's LARGEST NERF GUN!!","videoId":"57MKxz4pJKE","duration":219,"channelId":"UCY1kMZp36IQSyNx_9h4mpCg","uploadDate":"2016-06-21","channelName":"Mark Rober","link":"https://www.youtube.com/watch?v=57MKxz4pJKE","views":44480878},{"title":"World Record Domino Robot (100k dominoes in 24hrs)","videoId":"8HEfIJlcFbs","duration":876,"channelId":"UCY1kMZp36IQSyNx_9h4mpCg","uploadDate":"2021-07-26","channelName":"Mark Rober","link":"https://www.youtube.com/watch?v=8HEfIJlcFbs","views":44036673},{"title":"This Arcade Game is a SCAM (with proof)","videoId":"vXBfwgwT1nQ","duration":429,"channelId":"UCY1kMZp36IQSyNx_9h4mpCg","uploadDate":"2018-01-03","channelName":"Mark Rober","link":"https://www.youtube.com/watch?v=vXBfwgwT1nQ","views":43973001},{"title":"World's Largest Horn Shatters Glass","videoId":"pFEB0chiuJA","duration":556,"channelId":"UCY1kMZp36IQSyNx_9h4mpCg","uploadDate":"2018-11-28","channelName":"Mark Rober","link":"https://www.youtube.com/watch?v=pFEB0chiuJA","views":43913226},{"title":"NICEST Car Horn Ever- DIY","videoId":"lv8wqnk_TsA","duration":293,"channelId":"UCY1kMZp36IQSyNx_9h4mpCg","uploadDate":"2017-06-14","channelName":"Mark Rober","link":"https://www.youtube.com/watch?v=lv8wqnk_TsA","views":40193069},{"title":"How to measure HOW MUCH PEE IS IN YOUR POOL","videoId":"S32y9aYEzzo","duration":630,"channelId":"UCY1kMZp36IQSyNx_9h4mpCg","uploadDate":"2017-08-22","channelName":"Mark Rober","link":"https://www.youtube.com/watch?v=S32y9aYEzzo","views":38524796},{"title":"iPhone ATM PIN code hack- HOW TO PREVENT","videoId":"8Vc-69M-UWk","duration":226,"channelId":"UCY1kMZp36IQSyNx_9h4mpCg","uploadDate":"2014-08-28","channelName":"Mark Rober","link":"https://www.youtube.com/watch?v=8Vc-69M-UWk","views":38346101},{"title":"Egg Drop From Space","videoId":"BYVZh5kqaFg","duration":1617,"channelId":"UCY1kMZp36IQSyNx_9h4mpCg","uploadDate":"2022-11-25","channelName":"Mark Rober","link":"https://www.youtube.com/watch?v=BYVZh5kqaFg","views":37872134},{"title":"This Robot Eats Trash #TeamSeas","videoId":"pXDx6DjNLDU","duration":704,"channelId":"UCY1kMZp36IQSyNx_9h4mpCg","uploadDate":"2021-10-29","channelName":"Mark Rober","link":"https://www.youtube.com/watch?v=pXDx6DjNLDU","views":36341241},{"title":"1st place Egg Drop project ideas- using SCIENCE","videoId":"nsnyl8llfH4","duration":589,"channelId":"UCY1kMZp36IQSyNx_9h4mpCg","uploadDate":"2015-05-27","channelName":"Mark Rober","link":"https://www.youtube.com/watch?v=nsnyl8llfH4","views":35707363},{"title":"World's Tallest Elephant Toothpaste Volcano (I FINALLY DID IT!!)","videoId":"e09xig209cQ","duration":1029,"channelId":"UCY1kMZp36IQSyNx_9h4mpCg","uploadDate":"2021-09-04","channelName":"Mark Rober","link":"https://www.youtube.com/watch?v=e09xig209cQ","views":35663691},{"title":"The Truth About my Son","videoId":"ybPgmjTRvMo","duration":622,"channelId":"UCY1kMZp36IQSyNx_9h4mpCg","uploadDate":"2021-04-16","channelName":"Mark Rober","link":"https://www.youtube.com/watch?v=ybPgmjTRvMo","views":32498219},{"title":"200 dropped wallets- the 20 MOST and LEAST HONEST cities","videoId":"jnL7sJYblGY","duration":504,"channelId":"UCY1kMZp36IQSyNx_9h4mpCg","uploadDate":"2018-05-09","channelName":"Mark Rober","link":"https://www.youtube.com/watch?v=jnL7sJYblGY","views":32387624},{"title":"How To See Germs Spread Experiment (Coronavirus)","videoId":"I5-dI74zxPg","duration":517,"channelId":"UCY1kMZp36IQSyNx_9h4mpCg","uploadDate":"2020-03-18","channelName":"Mark Rober","link":"https://www.youtube.com/watch?v=I5-dI74zxPg","views":31071649},{"title":"CAR vs. WORLD’S STRONGEST TRAMPOLINE- 150ft (45m) drop","videoId":"tMKXbLBgkEc","duration":877,"channelId":"UCY1kMZp36IQSyNx_9h4mpCg","uploadDate":"2020-03-02","channelName":"Mark Rober","link":"https://www.youtube.com/watch?v=tMKXbLBgkEc","views":30678506},{"title":"EASY Pinewood Derby Car WINS using Science!!!","videoId":"-RjJtO51ykY","duration":959,"channelId":"UCY1kMZp36IQSyNx_9h4mpCg","uploadDate":"2014-04-16","channelName":"Mark Rober","link":"https://www.youtube.com/watch?v=-RjJtO51ykY","views":29360742},{"title":"BEAT ANY ESCAPE ROOM- 10 proven tricks and tips","videoId":"zwgaTYOx0RI","duration":683,"channelId":"UCY1kMZp36IQSyNx_9h4mpCg","uploadDate":"2018-08-29","channelName":"Mark Rober","link":"https://www.youtube.com/watch?v=zwgaTYOx0RI","views":28810044},{"title":"EXPLODING Glitter Bomb 4.0 vs. Package Thieves","videoId":"3c584TGG7jQ","duration":1108,"channelId":"UCY1kMZp36IQSyNx_9h4mpCg","uploadDate":"2021-12-13","channelName":"Mark Rober","link":"https://www.youtube.com/watch?v=3c584TGG7jQ","views":28072667},{"title":"World's Largest Lemon Battery- Lemon powered Supercar","videoId":"a1D-fZP8qJk","duration":724,"channelId":"UCY1kMZp36IQSyNx_9h4mpCg","uploadDate":"2018-06-23","channelName":"Mark Rober","link":"https://www.youtube.com/watch?v=a1D-fZP8qJk","views":28023506},{"title":"Car Thieves vs the Final GlitterBomb 5.0","videoId":"iWeu2dxHRDg","duration":1101,"channelId":"UCY1kMZp36IQSyNx_9h4mpCg","uploadDate":"2022-12-16","channelName":"Mark Rober","link":"https://www.youtube.com/watch?v=iWeu2dxHRDg","views":27898133},{"title":"BEST Guess Who Strategy- 96% WIN record using MATH","videoId":"FRlbNOno5VA","duration":745,"channelId":"UCY1kMZp36IQSyNx_9h4mpCg","uploadDate":"2015-11-17","channelName":"Mark Rober","link":"https://www.youtube.com/watch?v=FRlbNOno5VA","views":26399173},{"title":"Robot Piano Catches Fire Playing Rush E (World’s Hardest Song)","videoId":"uBEL3YVzMwk","duration":694,"channelId":"UCY1kMZp36IQSyNx_9h4mpCg","uploadDate":"2022-03-19","channelName":"Mark Rober","link":"https://www.youtube.com/watch?v=uBEL3YVzMwk","views":25829835},{"title":"Playing Card Machine Gun- Card Throwing Trick Shots","videoId":"GYCI58pMGuQ","duration":636,"channelId":"UCY1kMZp36IQSyNx_9h4mpCg","uploadDate":"2018-11-01","channelName":"Mark Rober","link":"https://www.youtube.com/watch?v=GYCI58pMGuQ","views":25646752},{"title":"Stealing Baseball Signs with a Phone (Machine Learning)","videoId":"PmlRbfSavbI","duration":810,"channelId":"UCY1kMZp36IQSyNx_9h4mpCg","uploadDate":"2019-06-30","channelName":"Mark Rober","link":"https://www.youtube.com/watch?v=PmlRbfSavbI","views":25102628},{"title":"Rocket Powered Golf Club at 100,000 FPS","videoId":"oBcxuzdP3rs","duration":879,"channelId":"UCY1kMZp36IQSyNx_9h4mpCg","uploadDate":"2019-03-31","channelName":"Mark Rober","link":"https://www.youtube.com/watch?v=oBcxuzdP3rs","views":23540188},{"title":"Using Drones to Plant 20,000,000 Trees","videoId":"U7nJBFjKqAY","duration":695,"channelId":"UCY1kMZp36IQSyNx_9h4mpCg","uploadDate":"2019-10-25","channelName":"Mark Rober","link":"https://www.youtube.com/watch?v=U7nJBFjKqAY","views":23018843},{"title":"Automatic Bullseye, MOVING DARTBOARD","videoId":"MHTizZ_XcUM","duration":337,"channelId":"UCY1kMZp36IQSyNx_9h4mpCg","uploadDate":"2017-03-21","channelName":"Mark Rober","link":"https://www.youtube.com/watch?v=MHTizZ_XcUM","views":22059653},{"title":"Rock Skip Robot- The Science of Perfect Rock Skipping","videoId":"M0_U1FHwACk","duration":562,"channelId":"UCY1kMZp36IQSyNx_9h4mpCg","uploadDate":"2018-07-31","channelName":"Mark Rober","link":"https://www.youtube.com/watch?v=M0_U1FHwACk","views":21318333},{"title":"I’ve Got a HUGE Secret Hiding Behind This Fake Office","videoId":"h8g9wfI9nGI","duration":1036,"channelId":"UCY1kMZp36IQSyNx_9h4mpCg","uploadDate":"2022-06-15","channelName":"Mark Rober","link":"https://www.youtube.com/watch?v=h8g9wfI9nGI","views":21083385},{"title":"Snowball Machine Gun- How to make","videoId":"JinpVA6p8Mo","duration":315,"channelId":"UCY1kMZp36IQSyNx_9h4mpCg","uploadDate":"2016-02-02","channelName":"Mark Rober","link":"https://www.youtube.com/watch?v=JinpVA6p8Mo","views":20493850},{"title":"1st place Mousetrap Car Ideas- using SCIENCE","videoId":"b7zWwo9dbiU","duration":846,"channelId":"UCY1kMZp36IQSyNx_9h4mpCg","uploadDate":"2018-03-29","channelName":"Mark Rober","link":"https://www.youtube.com/watch?v=b7zWwo9dbiU","views":20467608},{"title":"Backyard Squirrelympics 3.0- The Summer Games","videoId":"lg5wznn3IBE","duration":1395,"channelId":"UCY1kMZp36IQSyNx_9h4mpCg","uploadDate":"2022-10-23","channelName":"Mark Rober","link":"https://www.youtube.com/watch?v=lg5wznn3IBE","views":20457744},{"title":"Unbreakable Ice Cream Safe- How to make cool stuff (I made a class!)","videoId":"9e9D7ABgHpU","duration":538,"channelId":"UCY1kMZp36IQSyNx_9h4mpCg","uploadDate":"2020-12-08","channelName":"Mark Rober","link":"https://www.youtube.com/watch?v=9e9D7ABgHpU","views":20259656},{"title":"Watermelon smoothie hack in 2 minutes- No mess","videoId":"IJ-h0SO8EUI","duration":103,"channelId":"UCY1kMZp36IQSyNx_9h4mpCg","uploadDate":"2013-09-02","channelName":"Mark Rober","link":"https://www.youtube.com/watch?v=IJ-h0SO8EUI","views":20019343},{"title":"BARE HAND Bottle Busting- Science Investigation","videoId":"GMb6GNYPqXA","duration":326,"channelId":"UCY1kMZp36IQSyNx_9h4mpCg","uploadDate":"2016-08-31","channelName":"Mark Rober","link":"https://www.youtube.com/watch?v=GMb6GNYPqXA","views":19782004},{"title":"Amazing Invention- This Drone Will Change Everything","videoId":"DOWDNBu9DkU","duration":1292,"channelId":"UCY1kMZp36IQSyNx_9h4mpCg","uploadDate":"2023-03-18","channelName":"Mark Rober","link":"https://www.youtube.com/watch?v=DOWDNBu9DkU","views":17933586},{"title":"World's Largest T-Shirt Cannon (breaks the roof)","videoId":"QiKZYt9070U","duration":985,"channelId":"UCY1kMZp36IQSyNx_9h4mpCg","uploadDate":"2021-12-20","channelName":"Mark Rober","link":"https://www.youtube.com/watch?v=QiKZYt9070U","views":17849852},{"title":"Myth-testing Christmas movies with SCIENCE EXPERIMENTS (ft. Vsauce3)","videoId":"350Xlkvn0Ko","duration":509,"channelId":"UCY1kMZp36IQSyNx_9h4mpCg","uploadDate":"2016-12-15","channelName":"Mark Rober","link":"https://www.youtube.com/watch?v=350Xlkvn0Ko","views":16830926},{"title":"Shark vs. GoPro","videoId":"VS6tnF31zr4","duration":1387,"channelId":"UCY1kMZp36IQSyNx_9h4mpCg","uploadDate":"2021-07-12","channelName":"Mark Rober","link":"https://www.youtube.com/watch?v=VS6tnF31zr4","views":15854554},{"title":"Is NASA a waste of money?","videoId":"lARpY0nIQx0","duration":460,"channelId":"UCY1kMZp36IQSyNx_9h4mpCg","uploadDate":"2018-02-14","channelName":"Mark Rober","link":"https://www.youtube.com/watch?v=lARpY0nIQx0","views":15581638},{"title":"Perseverance Mars Rover Landing- Inside Story","videoId":"tH2tKigOPBU","duration":1038,"channelId":"UCY1kMZp36IQSyNx_9h4mpCg","uploadDate":"2021-02-15","channelName":"Mark Rober","link":"https://www.youtube.com/watch?v=tH2tKigOPBU","views":15501808},{"title":"How to save 51 billion lives for 68 cents with simple Engineering","videoId":"Qf-D1Upn-KU","duration":492,"channelId":"UCY1kMZp36IQSyNx_9h4mpCg","uploadDate":"2017-02-15","channelName":"Mark Rober","link":"https://www.youtube.com/watch?v=Qf-D1Upn-KU","views":15204810},{"title":"DRONE Solar System Model- How far is Planet 9?","videoId":"pR5VJo5ifdE","duration":503,"channelId":"UCY1kMZp36IQSyNx_9h4mpCg","uploadDate":"2016-03-09","channelName":"Mark Rober","link":"https://www.youtube.com/watch?v=pR5VJo5ifdE","views":14871033},{"title":"24 EASY Hi-Tech Halloween Costumes I invented","videoId":"qOQws77j_6c","duration":226,"channelId":"UCY1kMZp36IQSyNx_9h4mpCg","uploadDate":"2014-10-09","channelName":"Mark Rober","link":"https://www.youtube.com/watch?v=qOQws77j_6c","views":14146490},{"title":"Gut Ripping iPhone Halloween Costume + 17 more hi-tech costumes","videoId":"5rYhRn1x3FM","duration":210,"channelId":"UCY1kMZp36IQSyNx_9h4mpCg","uploadDate":"2013-10-07","channelName":"Mark Rober","link":"https://www.youtube.com/watch?v=5rYhRn1x3FM","views":13430389},{"title":"Defog your windows TWICE as fast using SCIENCE- 4 easy steps","videoId":"qCmgWiEEZwA","duration":316,"channelId":"UCY1kMZp36IQSyNx_9h4mpCg","uploadDate":"2016-01-05","channelName":"Mark Rober","link":"https://www.youtube.com/watch?v=qCmgWiEEZwA","views":12886069},{"title":"PAINT Super Soaker Battle (w/ Colin Furze)- Splatoon IRL","videoId":"_uXnypEzau0","duration":254,"channelId":"UCY1kMZp36IQSyNx_9h4mpCg","uploadDate":"2016-11-09","channelName":"Mark Rober","link":"https://www.youtube.com/watch?v=_uXnypEzau0","views":12730482},{"title":"Bed Bugs- What You've Been Told is Totally False","videoId":"2JAOTJxYqh8","duration":1427,"channelId":"UCY1kMZp36IQSyNx_9h4mpCg","uploadDate":"2023-03-04","channelName":"Mark Rober","link":"https://www.youtube.com/watch?v=2JAOTJxYqh8","views":11706179},{"title":"How to CHEER THE LOUDEST using SCIENCE!","videoId":"v4c0IBeXwY8","duration":383,"channelId":"UCY1kMZp36IQSyNx_9h4mpCg","uploadDate":"2016-11-29","channelName":"Mark Rober","link":"https://www.youtube.com/watch?v=v4c0IBeXwY8","views":11384639},{"title":"Unibrow Discrimination- Social Experiment","videoId":"MvnumV1izOE","duration":213,"channelId":"UCY1kMZp36IQSyNx_9h4mpCg","uploadDate":"2013-04-03","channelName":"Mark Rober","link":"https://www.youtube.com/watch?v=MvnumV1izOE","views":9385638},{"title":"Turtles or Snakes- Which do cars hit more? ROADKILL EXPERIMENT","videoId":"k-Fp7flAWMA","duration":262,"channelId":"UCY1kMZp36IQSyNx_9h4mpCg","uploadDate":"2012-07-19","channelName":"Mark Rober","link":"https://www.youtube.com/watch?v=k-Fp7flAWMA","views":8592898},{"title":"Hot Wheels STUNT RACE- Slow Mo (2500 FPS)","videoId":"vNds3PIBqnQ","duration":314,"channelId":"UCY1kMZp36IQSyNx_9h4mpCg","uploadDate":"2017-04-26","channelName":"Mark Rober","link":"https://www.youtube.com/watch?v=vNds3PIBqnQ","views":8230370},{"title":"1st place science fair ideas- 10 ideas and tricks to WIN!","videoId":"UBuH1b0Dqm0","duration":697,"channelId":"UCY1kMZp36IQSyNx_9h4mpCg","uploadDate":"2017-02-01","channelName":"Mark Rober","link":"https://www.youtube.com/watch?v=UBuH1b0Dqm0","views":8204997},{"title":"Color the Spectrum LIVE- Mark Rober and Jimmy Kimmel","videoId":"5J3peD8LZ5o","duration":10624,"channelId":"UCY1kMZp36IQSyNx_9h4mpCg","uploadDate":"2021-05-01","channelName":"Mark Rober","link":"https://www.youtube.com/watch?v=5J3peD8LZ5o","views":6168196},{"title":"FINAL SCIENCE CLASS- How to Survive a 5 Mile Fall with No Parachute","videoId":"3yjcqsNNa24","duration":2022,"channelId":"UCY1kMZp36IQSyNx_9h4mpCg","uploadDate":"2020-05-06","channelName":"Mark Rober","link":"https://www.youtube.com/watch?v=3yjcqsNNa24","views":6129287},{"title":"NASA's Curiosity landing- 1 of her creator's POV","videoId":"PCKogFDM3Zg","duration":278,"channelId":"UCY1kMZp36IQSyNx_9h4mpCg","uploadDate":"2012-08-15","channelName":"Mark Rober","link":"https://www.youtube.com/watch?v=PCKogFDM3Zg","views":6066179},{"title":"Beating iPhone Heart Halloween Costume + 20 more high-tech costumes","videoId":"fU0gs6KQ8jw","duration":227,"channelId":"UCY1kMZp36IQSyNx_9h4mpCg","uploadDate":"2012-10-03","channelName":"Mark Rober","link":"https://www.youtube.com/watch?v=fU0gs6KQ8jw","views":5983948},{"title":"GLOWING WALL DIY- EASY and AWESOME","videoId":"I6IqoSAtjb0","duration":423,"channelId":"UCY1kMZp36IQSyNx_9h4mpCg","uploadDate":"2016-10-11","channelName":"Mark Rober","link":"https://www.youtube.com/watch?v=I6IqoSAtjb0","views":5347807},{"title":"40 MPH Pinewood Derby Car- HOW TO","videoId":"vlBxPjxacsk","duration":96,"channelId":"UCY1kMZp36IQSyNx_9h4mpCg","uploadDate":"2014-04-16","channelName":"Mark Rober","link":"https://www.youtube.com/watch?v=vlBxPjxacsk","views":4846715},{"title":"NASA Pumpkin Carving Contest w/ LASERS!!!","videoId":"ZxbGGGh5I7M","duration":210,"channelId":"UCY1kMZp36IQSyNx_9h4mpCg","uploadDate":"2014-10-31","channelName":"Mark Rober","link":"https://www.youtube.com/watch?v=ZxbGGGh5I7M","views":4724229},{"title":"Scooby Doo Surveillance Cam (w/ 2 iPhones)","videoId":"sPgKu2E-jdw","duration":196,"channelId":"UCY1kMZp36IQSyNx_9h4mpCg","uploadDate":"2012-11-29","channelName":"Mark Rober","link":"https://www.youtube.com/watch?v=sPgKu2E-jdw","views":4635527},{"title":"Measure height with a watch! Cliff jump science","videoId":"z68vta3N5kg","duration":226,"channelId":"UCY1kMZp36IQSyNx_9h4mpCg","uploadDate":"2014-08-05","channelName":"Mark Rober","link":"https://www.youtube.com/watch?v=z68vta3N5kg","views":3367977},{"title":"HEAT MAP Microwave- a NEW invention","videoId":"ptkzzNaZb7U","duration":183,"channelId":"UCY1kMZp36IQSyNx_9h4mpCg","uploadDate":"2015-02-11","channelName":"Mark Rober","link":"https://www.youtube.com/watch?v=ptkzzNaZb7U","views":3324690},{"title":"Always win at heads/tails- BEST METHOD","videoId":"YdJr1FCB0P4","duration":354,"channelId":"UCY1kMZp36IQSyNx_9h4mpCg","uploadDate":"2012-01-18","channelName":"Mark Rober","link":"https://www.youtube.com/watch?v=YdJr1FCB0P4","views":3146846},{"title":"SCIENCE CLASS #2- Does Farting Make You Weigh Less?","videoId":"3FRyPjUlQKk","duration":1844,"channelId":"UCY1kMZp36IQSyNx_9h4mpCg","uploadDate":"2020-03-25","channelName":"Mark Rober","link":"https://www.youtube.com/watch?v=3FRyPjUlQKk","views":2981022},{"title":"LED Edge Lit Table- HOW TO","videoId":"SaG-NQ64540","duration":256,"channelId":"UCY1kMZp36IQSyNx_9h4mpCg","uploadDate":"2013-02-01","channelName":"Mark Rober","link":"https://www.youtube.com/watch?v=SaG-NQ64540","views":2243120},{"title":"SCIENCE CLASS #6- What if Everyone Flushed their Toilet at Once?","videoId":"nT6VWmeFIkc","duration":1441,"channelId":"UCY1kMZp36IQSyNx_9h4mpCg","uploadDate":"2020-04-08","channelName":"Mark Rober","link":"https://www.youtube.com/watch?v=nT6VWmeFIkc","views":2212668},{"title":"SCIENCE CLASS #1- WHY Does Helium Make Your Voice Higher?","videoId":"pPn-Bay_ANU","duration":2685,"channelId":"UCY1kMZp36IQSyNx_9h4mpCg","uploadDate":"2020-03-23","channelName":"Mark Rober","link":"https://www.youtube.com/watch?v=pPn-Bay_ANU","views":2132897},{"title":"SCIENCE CLASS #3- Why is the Sky Blue?","videoId":"zr359AIjU2Q","duration":1666,"channelId":"UCY1kMZp36IQSyNx_9h4mpCg","uploadDate":"2020-03-27","channelName":"Mark Rober","link":"https://www.youtube.com/watch?v=zr359AIjU2Q","views":1890695},{"title":"EPIC Matrix effect w/ a ceiling fan & 1 GoPro (ghetto bullet time)","videoId":"OEd5lTmeAH8","duration":210,"channelId":"UCY1kMZp36IQSyNx_9h4mpCg","uploadDate":"2013-05-09","channelName":"Mark Rober","link":"https://www.youtube.com/watch?v=OEd5lTmeAH8","views":1772090},{"title":"Gorilla lured by iPhone- how-to demo","videoId":"ZaOw8B_2kWY","duration":149,"channelId":"UCY1kMZp36IQSyNx_9h4mpCg","uploadDate":"2012-02-14","channelName":"Mark Rober","link":"https://www.youtube.com/watch?v=ZaOw8B_2kWY","views":1722328},{"title":"Freezing time w/ ONLY ONE camera, 360 degrees, 7200 fps","videoId":"INckJRRR1EU","duration":220,"channelId":"UCY1kMZp36IQSyNx_9h4mpCg","uploadDate":"2013-12-05","channelName":"Mark Rober","link":"https://www.youtube.com/watch?v=INckJRRR1EU","views":1681467},{"title":"8-bit Annoying Person Remover- NES Hack","videoId":"QW5L2fMriZk","duration":159,"channelId":"UCY1kMZp36IQSyNx_9h4mpCg","uploadDate":"2013-02-28","channelName":"Mark Rober","link":"https://www.youtube.com/watch?v=QW5L2fMriZk","views":1536628},{"title":"Whiteboard Office Darts (using BuckyBalls)","videoId":"7sj6Gpk3ab4","duration":110,"channelId":"UCY1kMZp36IQSyNx_9h4mpCg","uploadDate":"2011-12-19","channelName":"Mark Rober","link":"https://www.youtube.com/watch?v=7sj6Gpk3ab4","views":1280449},{"title":"SCIENCE CLASS #5- How Do Astronauts Weigh Themselves?","videoId":"DKHEanz5ayM","duration":1380,"channelId":"UCY1kMZp36IQSyNx_9h4mpCg","uploadDate":"2020-04-03","channelName":"Mark Rober","link":"https://www.youtube.com/watch?v=DKHEanz5ayM","views":1211741},{"title":"SCIENCE CLASS #4- How to Waterproof Your Hand","videoId":"00aZJP4kmK4","duration":1660,"channelId":"UCY1kMZp36IQSyNx_9h4mpCg","uploadDate":"2020-03-30","channelName":"Mark Rober","link":"https://www.youtube.com/watch?v=00aZJP4kmK4","views":965725},{"title":"Glowing Algae Water Fountain","videoId":"mDmFSz8-r7g","duration":168,"channelId":"UCY1kMZp36IQSyNx_9h4mpCg","uploadDate":"2013-07-30","channelName":"Mark Rober","link":"https://www.youtube.com/watch?v=mDmFSz8-r7g","views":909365},{"title":"250 sq ft GLOWING Super Mario night kite","videoId":"jOTu4s0nzJM","duration":189,"channelId":"UCY1kMZp36IQSyNx_9h4mpCg","uploadDate":"2012-06-07","channelName":"Mark Rober","link":"https://www.youtube.com/watch?v=jOTu4s0nzJM","views":776287},{"title":"Burning Fireplace Ugly Christmas Sweater (w/ an iPad)","videoId":"81YUiTnTVJw","duration":136,"channelId":"UCY1kMZp36IQSyNx_9h4mpCg","uploadDate":"2012-12-07","channelName":"Mark Rober","link":"https://www.youtube.com/watch?v=81YUiTnTVJw","views":464131}]}