{"channel":252,"channelName":"megadethvevo","content":[{"title":"Megadeth - Holy Wars...The Punishment Due","videoId":"9d4ui9q7eDM","duration":398,"channelId":"UC-Ugu5IBFgrYuHBAW2DjmZQ","uploadDate":"2009-03-12","channelName":"Megadeth","link":"https://www.youtube.com/watch?v=9d4ui9q7eDM","views":59205698},{"title":"Megadeth - Sweating Bullets (Official Music Video)","videoId":"aOnKCcjP8Qs","duration":261,"channelId":"UC-Ugu5IBFgrYuHBAW2DjmZQ","uploadDate":"2009-02-26","channelName":"Megadeth","link":"https://www.youtube.com/watch?v=aOnKCcjP8Qs","views":27797973},{"title":"Megadeth - A Tout Le Monde (Official Music Video)","videoId":"aU-dKoFZT0A","duration":254,"channelId":"UC-Ugu5IBFgrYuHBAW2DjmZQ","uploadDate":"2009-03-12","channelName":"Megadeth","link":"https://www.youtube.com/watch?v=aU-dKoFZT0A","views":23278061},{"title":"Megadeth - In My Darkest Hour (Official Music Video)","videoId":"mW0Ao9r2zkY","duration":313,"channelId":"UC-Ugu5IBFgrYuHBAW2DjmZQ","uploadDate":"2009-03-12","channelName":"Megadeth","link":"https://www.youtube.com/watch?v=mW0Ao9r2zkY","views":10934413},{"title":"Megadeth - Dystopia (Official Music Video)","videoId":"bK95lWHl7js","duration":316,"channelId":"UC-Ugu5IBFgrYuHBAW2DjmZQ","uploadDate":"2016-01-21","channelName":"Megadeth","link":"https://www.youtube.com/watch?v=bK95lWHl7js","views":8850442},{"title":"Megadeth - Post American World (Official Music Video)","videoId":"mEkXyEIu3OU","duration":283,"channelId":"UC-Ugu5IBFgrYuHBAW2DjmZQ","uploadDate":"2016-07-19","channelName":"Megadeth","link":"https://www.youtube.com/watch?v=mEkXyEIu3OU","views":8364567},{"title":"Megadeth - The Threat Is Real (Official Video)","videoId":"3-d6LFLpBvw","duration":272,"channelId":"UC-Ugu5IBFgrYuHBAW2DjmZQ","uploadDate":"2015-12-11","channelName":"Megadeth","link":"https://www.youtube.com/watch?v=3-d6LFLpBvw","views":8166765},{"title":"Megadeth - Conquer Or Die (Official Video)","videoId":"dQ_-tUKT-nY","duration":215,"channelId":"UC-Ugu5IBFgrYuHBAW2DjmZQ","uploadDate":"2016-09-24","channelName":"Megadeth","link":"https://www.youtube.com/watch?v=dQ_-tUKT-nY","views":7998074},{"title":"Megadeth - Wake Up Dead (Official Music Video)","videoId":"4kSvN1dQjxc","duration":246,"channelId":"UC-Ugu5IBFgrYuHBAW2DjmZQ","uploadDate":"2009-03-12","channelName":"Megadeth","link":"https://www.youtube.com/watch?v=4kSvN1dQjxc","views":7720662},{"title":"Megadeth - Symphony of Destruction (VEVO Presents)","videoId":"JCRv_DnAZQs","duration":252,"channelId":"UC-Ugu5IBFgrYuHBAW2DjmZQ","uploadDate":"2013-08-30","channelName":"Megadeth","link":"https://www.youtube.com/watch?v=JCRv_DnAZQs","views":7238152},{"title":"Megadeth - Fatal Illusion (Audio)","videoId":"7MRtdd3tXI4","duration":257,"channelId":"UC-Ugu5IBFgrYuHBAW2DjmZQ","uploadDate":"2015-10-01","channelName":"Megadeth","link":"https://www.youtube.com/watch?v=7MRtdd3tXI4","views":6371506},{"title":"Megadeth - Foreclosure Of A Dream (Official Music Video)","videoId":"RgikGBh6pbI","duration":290,"channelId":"UC-Ugu5IBFgrYuHBAW2DjmZQ","uploadDate":"2009-03-12","channelName":"Megadeth","link":"https://www.youtube.com/watch?v=RgikGBh6pbI","views":5343179},{"title":"Megadeth - Symphony Of Destruction","videoId":"vfpgpf6QVnI","duration":259,"channelId":"UC-Ugu5IBFgrYuHBAW2DjmZQ","uploadDate":"2010-04-24","channelName":"Megadeth","link":"https://www.youtube.com/watch?v=vfpgpf6QVnI","views":4940696},{"title":"Megadeth - Dystopia (Audio)","videoId":"QrV61ATP3Ec","duration":300,"channelId":"UC-Ugu5IBFgrYuHBAW2DjmZQ","uploadDate":"2016-01-07","channelName":"Megadeth","link":"https://www.youtube.com/watch?v=QrV61ATP3Ec","views":4663528},{"title":"Megadeth - Lying In State","videoId":"yFxsnOm2kLg","duration":274,"channelId":"UC-Ugu5IBFgrYuHBAW2DjmZQ","uploadDate":"2018-02-01","channelName":"Megadeth","link":"https://www.youtube.com/watch?v=yFxsnOm2kLg","views":4516440},{"title":"Megadeth - Peace Sells","videoId":"rdEupVsL07E","duration":252,"channelId":"UC-Ugu5IBFgrYuHBAW2DjmZQ","uploadDate":"2010-11-17","channelName":"Megadeth","link":"https://www.youtube.com/watch?v=rdEupVsL07E","views":4499353},{"title":"Megadeth - We’ll Be Back: Chapter I","videoId":"LkJ5jJuraLQ","duration":312,"channelId":"UC-Ugu5IBFgrYuHBAW2DjmZQ","uploadDate":"2022-06-23","channelName":"Megadeth","link":"https://www.youtube.com/watch?v=LkJ5jJuraLQ","views":4108652},{"title":"Megadeth - Super Collider","videoId":"PZhqZAVGTqw","duration":252,"channelId":"UC-Ugu5IBFgrYuHBAW2DjmZQ","uploadDate":"2013-07-03","channelName":"Megadeth","link":"https://www.youtube.com/watch?v=PZhqZAVGTqw","views":3931755},{"title":"Megadeth - She Wolf (VEVO Presents)","videoId":"YsV3BXb0wNI","duration":249,"channelId":"UC-Ugu5IBFgrYuHBAW2DjmZQ","uploadDate":"2013-08-30","channelName":"Megadeth","link":"https://www.youtube.com/watch?v=YsV3BXb0wNI","views":3892284},{"title":"Megadeth - Poisonous Shadows (Live) (360)","videoId":"unQZvhQ9Giw","duration":375,"channelId":"UC-Ugu5IBFgrYuHBAW2DjmZQ","uploadDate":"2016-04-25","channelName":"Megadeth","link":"https://www.youtube.com/watch?v=unQZvhQ9Giw","views":3633405},{"title":"Megadeth - Go To Hell","videoId":"a7pqj8Be8kU","duration":274,"channelId":"UC-Ugu5IBFgrYuHBAW2DjmZQ","uploadDate":"2009-03-12","channelName":"Megadeth","link":"https://www.youtube.com/watch?v=a7pqj8Be8kU","views":3236671},{"title":"Megadeth - Night Stalkers: Chapter II ft. Ice-T","videoId":"wAqc_zfmML0","duration":415,"channelId":"UC-Ugu5IBFgrYuHBAW2DjmZQ","uploadDate":"2022-07-22","channelName":"Megadeth","link":"https://www.youtube.com/watch?v=wAqc_zfmML0","views":2887232},{"title":"Megadeth - Hangar 18","videoId":"rUGIocJK9Tc","duration":242,"channelId":"UC-Ugu5IBFgrYuHBAW2DjmZQ","uploadDate":"2010-04-23","channelName":"Megadeth","link":"https://www.youtube.com/watch?v=rUGIocJK9Tc","views":2710473},{"title":"Megadeth - Almost Honest","videoId":"Fh9Ixvfyzf0","duration":242,"channelId":"UC-Ugu5IBFgrYuHBAW2DjmZQ","uploadDate":"2009-03-12","channelName":"Megadeth","link":"https://www.youtube.com/watch?v=Fh9Ixvfyzf0","views":2103299},{"title":"Megadeth - The Threat Is Real (Audio)","videoId":"4mfjpwqdUMI","duration":262,"channelId":"UC-Ugu5IBFgrYuHBAW2DjmZQ","uploadDate":"2015-11-27","channelName":"Megadeth","link":"https://www.youtube.com/watch?v=4mfjpwqdUMI","views":1789165},{"title":"Megadeth - Reckoning Day","videoId":"QiMb08L2-cg","duration":292,"channelId":"UC-Ugu5IBFgrYuHBAW2DjmZQ","uploadDate":"2009-03-12","channelName":"Megadeth","link":"https://www.youtube.com/watch?v=QiMb08L2-cg","views":1704289},{"title":"Megadeth - The Sick, The Dying… And The Dead!: Chapter III","videoId":"xc_mfqPS2LY","duration":338,"channelId":"UC-Ugu5IBFgrYuHBAW2DjmZQ","uploadDate":"2022-09-02","channelName":"Megadeth","link":"https://www.youtube.com/watch?v=xc_mfqPS2LY","views":1633997},{"title":"Megadeth - Soldier On! (Visualizer)","videoId":"q5M8K2Jm2bE","duration":295,"channelId":"UC-Ugu5IBFgrYuHBAW2DjmZQ","uploadDate":"2022-08-12","channelName":"Megadeth","link":"https://www.youtube.com/watch?v=q5M8K2Jm2bE","views":1428593},{"title":"Megadeth - Hangar 18 (Vic and the Rattleheads - Live at St. Vitus, 2016)","videoId":"41IoDigg72A","duration":368,"channelId":"UC-Ugu5IBFgrYuHBAW2DjmZQ","uploadDate":"2020-07-10","channelName":"Megadeth","link":"https://www.youtube.com/watch?v=41IoDigg72A","views":1241209},{"title":"Megadeth - Kingmaker (VEVO Presents)","videoId":"z3oJgGaQOYA","duration":258,"channelId":"UC-Ugu5IBFgrYuHBAW2DjmZQ","uploadDate":"2013-08-30","channelName":"Megadeth","link":"https://www.youtube.com/watch?v=z3oJgGaQOYA","views":1147440},{"title":"Megadeth - Life In Hell: Chapter IV (Official Music Video)","videoId":"lW_Xyj1sIBQ","duration":314,"channelId":"UC-Ugu5IBFgrYuHBAW2DjmZQ","uploadDate":"2022-10-20","channelName":"Megadeth","link":"https://www.youtube.com/watch?v=lW_Xyj1sIBQ","views":1126491},{"title":"Megadeth - Killing Time: Chapter V","videoId":"pvVJH3dKQBU","duration":359,"channelId":"UC-Ugu5IBFgrYuHBAW2DjmZQ","uploadDate":"2022-12-16","channelName":"Megadeth","link":"https://www.youtube.com/watch?v=pvVJH3dKQBU","views":1077964},{"title":"Megadeth - Countdown To Extinction (Live At The Fox Theater/2012)","videoId":"iYzUIKnGVvk","duration":257,"channelId":"UC-Ugu5IBFgrYuHBAW2DjmZQ","uploadDate":"2013-09-27","channelName":"Megadeth","link":"https://www.youtube.com/watch?v=iYzUIKnGVvk","views":1016350},{"title":"Holy Wars...The Punishment Due (Vic and The Rattleheads - Live at St. Vitus, 2016)","videoId":"q9OzwKGmEmE","duration":467,"channelId":"UC-Ugu5IBFgrYuHBAW2DjmZQ","uploadDate":"2020-08-28","channelName":"Megadeth","link":"https://www.youtube.com/watch?v=q9OzwKGmEmE","views":974263},{"title":"Megadeth - Trust","videoId":"keRMhpjjn_U","duration":257,"channelId":"UC-Ugu5IBFgrYuHBAW2DjmZQ","uploadDate":"2010-04-23","channelName":"Megadeth","link":"https://www.youtube.com/watch?v=keRMhpjjn_U","views":900732},{"title":"Megadeth - Train Of Consequences","videoId":"-G38VlmOib8","duration":222,"channelId":"UC-Ugu5IBFgrYuHBAW2DjmZQ","uploadDate":"2010-04-24","channelName":"Megadeth","link":"https://www.youtube.com/watch?v=-G38VlmOib8","views":608690},{"title":"Megadeth - Last Rites / Loved to Deth (Audio)","videoId":"l5yK9oW1M38","duration":294,"channelId":"UC-Ugu5IBFgrYuHBAW2DjmZQ","uploadDate":"2019-04-24","channelName":"Megadeth","link":"https://www.youtube.com/watch?v=l5yK9oW1M38","views":527704},{"title":"Megadeth - Tornado Of Souls (Vic and The Rattleheads - Live at St. Vitus, 2016)","videoId":"OmNwBlr0Kkk","duration":326,"channelId":"UC-Ugu5IBFgrYuHBAW2DjmZQ","uploadDate":"2020-07-24","channelName":"Megadeth","link":"https://www.youtube.com/watch?v=OmNwBlr0Kkk","views":480643},{"title":"Megadeth - The Skull Beneath the Skin (Audio)","videoId":"yLPTsk707gA","duration":226,"channelId":"UC-Ugu5IBFgrYuHBAW2DjmZQ","uploadDate":"2018-05-25","channelName":"Megadeth","link":"https://www.youtube.com/watch?v=yLPTsk707gA","views":417446},{"title":"Megadeth - Anarchy In The UK","videoId":"Wj9_YtUNIj8","duration":189,"channelId":"UC-Ugu5IBFgrYuHBAW2DjmZQ","uploadDate":"2010-04-23","channelName":"Megadeth","link":"https://www.youtube.com/watch?v=Wj9_YtUNIj8","views":356904},{"title":"Megadeth - Peace Sells (Vic and The Rattleheads - Live at St. Vitus, 2016)","videoId":"kvgCamY3dtY","duration":267,"channelId":"UC-Ugu5IBFgrYuHBAW2DjmZQ","uploadDate":"2020-08-21","channelName":"Megadeth","link":"https://www.youtube.com/watch?v=kvgCamY3dtY","views":331778},{"title":"Megadeth - Symphony Of Destruction (Vic and The Rattleheads - Live at St. Vitus, 2016)","videoId":"PAytGMOegGU","duration":230,"channelId":"UC-Ugu5IBFgrYuHBAW2DjmZQ","uploadDate":"2020-08-14","channelName":"Megadeth","link":"https://www.youtube.com/watch?v=PAytGMOegGU","views":290613},{"title":"Megadeth - Dystopia VR Behind The Scenes (Full Version)","videoId":"gZY0yGU3__M","duration":321,"channelId":"UC-Ugu5IBFgrYuHBAW2DjmZQ","uploadDate":"2016-01-30","channelName":"Megadeth","link":"https://www.youtube.com/watch?v=gZY0yGU3__M","views":261166},{"title":"Megadeth - Sweating Bullets (Vic and the Rattleheads - Live at St. Vitus, 2016)","videoId":"EcUuyqf1UPw","duration":300,"channelId":"UC-Ugu5IBFgrYuHBAW2DjmZQ","uploadDate":"2020-07-31","channelName":"Megadeth","link":"https://www.youtube.com/watch?v=EcUuyqf1UPw","views":217352},{"title":"Megadeth - Rattlehead (Vic and the Rattleheads - Live at St. Vitus, 2016)","videoId":"U4ojqf-lxhY","duration":247,"channelId":"UC-Ugu5IBFgrYuHBAW2DjmZQ","uploadDate":"2020-07-17","channelName":"Megadeth","link":"https://www.youtube.com/watch?v=U4ojqf-lxhY","views":193809},{"title":"Megadeth - Dystopia (Vic and the Rattleheads - Live at St. Vitus, 2016)","videoId":"X23afHWVj_Q","duration":300,"channelId":"UC-Ugu5IBFgrYuHBAW2DjmZQ","uploadDate":"2020-08-07","channelName":"Megadeth","link":"https://www.youtube.com/watch?v=X23afHWVj_Q","views":192413},{"title":"Megadeth - Dave Mustaine Visits School Of Rock","videoId":"Flh2RHe3XRI","duration":197,"channelId":"UC-Ugu5IBFgrYuHBAW2DjmZQ","uploadDate":"2016-04-01","channelName":"Megadeth","link":"https://www.youtube.com/watch?v=Flh2RHe3XRI","views":158927},{"title":"Megadeth - Holy Wars (Live)","videoId":"sPyf_IGaPAY","duration":388,"channelId":"UC-Ugu5IBFgrYuHBAW2DjmZQ","uploadDate":"2013-11-07","channelName":"Megadeth","link":"https://www.youtube.com/watch?v=sPyf_IGaPAY","views":157896},{"title":"Megadeth - Fashion statements (Rock On The Range)","videoId":"j2AtcNxbLc8","duration":390,"channelId":"UC-Ugu5IBFgrYuHBAW2DjmZQ","uploadDate":"2016-06-09","channelName":"Megadeth","link":"https://www.youtube.com/watch?v=j2AtcNxbLc8","views":62292},{"title":"Megadeth - Dystopia VR Behind The Scenes (Part 2)","videoId":"9QplCkLkxWI","duration":103,"channelId":"UC-Ugu5IBFgrYuHBAW2DjmZQ","uploadDate":"2016-01-26","channelName":"Megadeth","link":"https://www.youtube.com/watch?v=9QplCkLkxWI","views":41192},{"title":"Megadeth - Dystopia VR Behind The Scenes (Part 1)","videoId":"9KtUFQ3s8VE","duration":98,"channelId":"UC-Ugu5IBFgrYuHBAW2DjmZQ","uploadDate":"2016-01-29","channelName":"Megadeth","link":"https://www.youtube.com/watch?v=9KtUFQ3s8VE","views":28993},{"title":"Megadeth - Dystopia VR Behind The Scenes (Part 3)","videoId":"hBgk3y9PxXA","duration":96,"channelId":"UC-Ugu5IBFgrYuHBAW2DjmZQ","uploadDate":"2016-03-25","channelName":"Megadeth","link":"https://www.youtube.com/watch?v=hBgk3y9PxXA","views":17721}]}